layerxtr/__init__.py
layerxtr/main.py
layerxtr/prompts.py
layerxtr-2025.12.22082716.dist-info/METADATA
layerxtr-2025.12.22082716.dist-info/WHEEL
layerxtr-2025.12.22082716.dist-info/top_level.txt
layerxtr-2025.12.22082716.dist-info/RECORD
