Metadata-Version: 2.4
Name: layerxtr
Version: 2025.12.22082716
Summary: Layerxtr extracts layer details from text, structuring them for designers to auto replicate images.
Author-email: layerxtr <hi@eugene.plus>
License: MIT
Project-URL: Homepage, https://github.com/chigwell/layerxtr
Requires-Python: >=3.9
Requires-Dist: langchain-llm7>=0.0.0
Requires-Dist: llmatch-messages>=0.0.0
Requires-Dist: langchain-core>=0.3.0
